{
  "tenantid": "dl",
  "moduleName": "swm",
  "CollectionType": [
    {
      "tenantid": "dl",
      "name": "Door to Door Collection (Wet \u0026 Dry)",
      "code": "Collection Type Code 1"
    },
    {
      "tenantid": "dl",
      "name": "(Day to Day Basis)",
      "code": "Collection Type Code 2"
    },
    {
      "tenantid": "dl",
      "name": "Collection from collection point",
      "code": "Collection Type Code 3"
    },
    {
      "tenantid": "dl",
      "name": "From demolished apartments",
      "code": "asdsad"
    },
    {
      "tenantid": "dl",
      "name": "Weekly Collection (Door to Door)",
      "code": "Weekly Collection"
    },
    {
      "tenantid": "dl",
      "name": "Test Collection",
      "code": "Test Collection"
    },
    {
      "tenantid": "dl",
      "name": "CP Name",
      "code": "CPN"
    },
    {
      "tenantid": "dl",
      "name": "CT Name",
      "code": "CTN"
    },
    {
      "tenantid": "dl",
      "name": "12",
      "code": "11"
    },
    {
      "tenantid": "dl",
      "name": "Coll Type updated",
      "code": "CTS"
    },
    {
      "tenantid": "dl",
      "name": "From Dust Bin",
      "code": "FDB"
    },
    {
      "tenantid": "dl",
      "name": "Door To Door",
      "code": "CollectionTypeCode001"
    },
    {
      "tenantid": "dl",
      "name": "Road Bin",
      "code": "RB"
    },
    {
      "tenantid": "dl",
      "name": "Wastage",
      "code": "WASTAGE"
    },
    {
      "tenantid": "dl",
      "name": "TTT",
      "code": "Test"
    },
    {
      "tenantid": "dl",
      "name": "TestForTest",
      "code": "TFT"
    },
    {
      "tenantid": "dl",
      "name": "VVV",
      "code": "VVV"
    },
    {
      "tenantid": "dl",
      "name": "NNN",
      "code": "NNN"
    },
    {
      "tenantid": "dl",
      "name": "CCC",
      "code": "CSD"
    },
    {
      "tenantid": "dl",
      "name": "KKK",
      "code": "KKK"
    },
    {
      "tenantid": "dl",
      "name": "New CT Test 101",
      "code": "CT 101"
    },
    {
      "tenantid": "dl",
      "name": "M_Collection_Point",
      "code": "MCollect"
    },
    {
      "tenantid": "dl",
      "name": "M_Colleaction_Point_2",
      "code": "MCollection"
    },
    {
      "tenantid": "dl",
      "name": "New Collection Type 23",
      "code": "NCT 23"
    },
    {
      "tenantid": "dl",
      "name": "Collection Type 24",
      "code": "CT 24"
    },
    {
      "tenantid": "dl",
      "name": "ttt",
      "code": "TTT"
    },
    {
      "tenantid": "dl",
      "name": "RRR",
      "code": "RRR"
    },
    {
      "tenantid": "dl",
      "name": "COll Type 999",
      "code": "CT999"
    },
    {
      "tenantid": "dl",
      "name": "mmmm",
      "code": "MMM"
    },
    {
      "tenantid": "dl",
      "name": "CT Dev",
      "code": "CTD 1"
    },
    {
      "tenantid": "dl",
      "name": "CT Name 999",
      "code": "CTN 999"
    },
    {
      "tenantid": "dl",
      "name": "Collection Test 101",
      "code": "CT Test 101"
    },
    {
      "tenantid": "dl",
      "name": "Test 2424",
      "code": "CT 2424"
    },
    {
      "tenantid": "dl",
      "name": "Test 2525",
      "code": "CT 2525"
    }
  ]
}